fastgenerateapi/__init__.py
fastgenerateapi/__version__.py
fastgenerateapi/api_view/__init__.py
fastgenerateapi/api_view/api_view.py
fastgenerateapi/api_view/base_view.py
fastgenerateapi/api_view/create_view.py
fastgenerateapi/api_view/delete_filter_view.py
fastgenerateapi/api_view/delete_tree_view.py
fastgenerateapi/api_view/delete_view.py
fastgenerateapi/api_view/get_all_view.py
fastgenerateapi/api_view/get_one_view.py
fastgenerateapi/api_view/get_relation_view.py
fastgenerateapi/api_view/get_tree_view.py
fastgenerateapi/api_view/switch_view.py
fastgenerateapi/api_view/update_relation_view.py
fastgenerateapi/api_view/update_view.py
fastgenerateapi/api_view/mixin/__init__.py
fastgenerateapi/api_view/mixin/base_mixin.py
fastgenerateapi/api_view/mixin/dbmodel_mixin.py
fastgenerateapi/api_view/mixin/get_mixin.py
fastgenerateapi/api_view/mixin/response_mixin.py
fastgenerateapi/api_view/mixin/save_mixin.py
fastgenerateapi/api_view/mixin/tool_mixin.py
fastgenerateapi/api_view/mixin/utils/__init__.py
fastgenerateapi/cache/__init__.py
fastgenerateapi/cache/cache_decorator.py
fastgenerateapi/cache/key_builder.py
fastgenerateapi/channel/__init__.py
fastgenerateapi/channel/connection_manager.py
fastgenerateapi/channel/consumer.py
fastgenerateapi/channel/websocket_view.py
fastgenerateapi/controller/__init__.py
fastgenerateapi/controller/filter_controller.py
fastgenerateapi/controller/router_controller.py
fastgenerateapi/controller/rpc_controller.py
fastgenerateapi/controller/search_controller.py
fastgenerateapi/controller/ws_controller.py
fastgenerateapi/data_type/__init__.py
fastgenerateapi/data_type/data_type.py
fastgenerateapi/data_type/mysql_data_type.py
fastgenerateapi/data_type/tortoise_type.py
fastgenerateapi/deps/__init__.py
fastgenerateapi/deps/filter_params_deps.py
fastgenerateapi/deps/tree_params_deps.py
fastgenerateapi/example/__init__.py
fastgenerateapi/example/models.py
fastgenerateapi/example/routers.py
fastgenerateapi/example/schemas.py
fastgenerateapi-1.2.29.dist-info/LICENSE
fastgenerateapi-1.2.29.dist-info/METADATA
fastgenerateapi-1.2.29.dist-info/WHEEL
fastgenerateapi-1.2.29.dist-info/top_level.txt
fastgenerateapi-1.2.29.dist-info/RECORD
